<?xml version="1.0"?>

<pingus-level>
  <global>
    <levelname lang="en">Pingu Acceleration Labs</levelname>
    <description lang="en"></description>
    <author>Craig Timpany &lt;timpany@pingus.cx&gt;</author>
    <number-of-pingus>100</number-of-pingus>
    <number-to-save>70</number-to-save>
    <time>9000</time>
    <width>800</width>
    <height>928</height>
  </global>

<background type="surface">
  <surface><resource type="datafile">
    <resource-datafile>textures</resource-datafile>
  <resource-ident>Textures/rooftile</resource-ident>
  </resource></surface>
  <color>
    <red>0</red>
    <green>0</green>
    <blue>0</blue>
    <alpha>1</alpha>
  </color>
  <scroll-x>0</scroll-x>
  <scroll-y>0</scroll-y>
  <para-x>0.5</para-x>
  <para-y>0.5</para-y>
  <stretch-x>0</stretch-x>
  <stretch-y>0</stretch-y>
</background>
  <action-list>
    <digger>10</digger>
    <basher>10</basher>
    <blocker>3</blocker>
    <bridger>1</bridger>
    <floater>1</floater>
  </action-list>

<groundpiece type="solid">
  <surface><resource type="datafile">
    <resource-datafile>global</resource-datafile>
  <resource-ident>GroundPieces/Misc/middleprickpiece</resource-ident>
  </resource></surface>
  <position>
    <x-pos>27</x-pos>
    <y-pos>822</y-pos>
    <z-pos>0</z-pos>
  </position>
</groundpiece>

<groundpiece type="solid">
  <surface><resource type="datafile">
    <resource-datafile>global</resource-datafile>
  <resource-ident>GroundPieces/Misc/middleprickpiece</resource-ident>
  </resource></surface>
  <position>
    <x-pos>627</x-pos>
    <y-pos>822</y-pos>
    <z-pos>0</z-pos>
  </position>
</groundpiece>

<groundpiece type="solid">
  <surface><resource type="datafile">
    <resource-datafile>global</resource-datafile>
  <resource-ident>GroundPieces/Misc/middleprickpiece</resource-ident>
  </resource></surface>
  <position>
    <x-pos>477</x-pos>
    <y-pos>822</y-pos>
    <z-pos>0</z-pos>
  </position>
</groundpiece>

<groundpiece type="solid">
  <surface><resource type="datafile">
    <resource-datafile>global</resource-datafile>
  <resource-ident>GroundPieces/Misc/middleprickpiece</resource-ident>
  </resource></surface>
  <position>
    <x-pos>177</x-pos>
    <y-pos>822</y-pos>
    <z-pos>0</z-pos>
  </position>
</groundpiece>

<groundpiece type="solid">
  <surface><resource type="datafile">
    <resource-datafile>global</resource-datafile>
  <resource-ident>GroundPieces/Misc/middleprickpiece</resource-ident>
  </resource></surface>
  <position>
    <x-pos>327</x-pos>
    <y-pos>822</y-pos>
    <z-pos>0</z-pos>
  </position>
</groundpiece>

<groundpiece type="ground">
  <surface><resource type="datafile">
    <resource-datafile>global</resource-datafile>
  <resource-ident>GroundPieces/Misc/stoneblock3</resource-ident>
  </resource></surface>
  <position>
    <x-pos>358</x-pos>
    <y-pos>668</y-pos>
    <z-pos>0</z-pos>
  </position>
</groundpiece>

<groundpiece type="ground">
  <surface><resource type="datafile">
    <resource-datafile>global</resource-datafile>
  <resource-ident>GroundPieces/Misc/stoneblock3</resource-ident>
  </resource></surface>
  <position>
    <x-pos>358</x-pos>
    <y-pos>604</y-pos>
    <z-pos>0</z-pos>
  </position>
</groundpiece>

<groundpiece type="ground">
  <surface><resource type="datafile">
    <resource-datafile>global</resource-datafile>
  <resource-ident>GroundPieces/Misc/stoneblock3</resource-ident>
  </resource></surface>
  <position>
    <x-pos>359</x-pos>
    <y-pos>334</y-pos>
    <z-pos>0</z-pos>
  </position>
</groundpiece>

<groundpiece type="ground">
  <surface><resource type="datafile">
    <resource-datafile>global</resource-datafile>
  <resource-ident>GroundPieces/Misc/stoneblock3</resource-ident>
  </resource></surface>
  <position>
    <x-pos>358</x-pos>
    <y-pos>540</y-pos>
    <z-pos>0</z-pos>
  </position>
</groundpiece>

<groundpiece type="ground">
  <surface><resource type="datafile">
    <resource-datafile>global</resource-datafile>
  <resource-ident>GroundPieces/Misc/stoneblock3</resource-ident>
  </resource></surface>
  <position>
    <x-pos>359</x-pos>
    <y-pos>270</y-pos>
    <z-pos>0</z-pos>
  </position>
</groundpiece>

<groundpiece type="ground">
  <surface><resource type="datafile">
    <resource-datafile>global</resource-datafile>
  <resource-ident>GroundPieces/Misc/stoneblock3</resource-ident>
  </resource></surface>
  <position>
    <x-pos>359</x-pos>
    <y-pos>398</y-pos>
    <z-pos>0</z-pos>
  </position>
</groundpiece>

<groundpiece type="ground">
  <surface><resource type="datafile">
    <resource-datafile>global</resource-datafile>
  <resource-ident>GroundPieces/Misc/stoneblock3</resource-ident>
  </resource></surface>
  <position>
    <x-pos>359</x-pos>
    <y-pos>142</y-pos>
    <z-pos>0</z-pos>
  </position>
</groundpiece>

<groundpiece type="ground">
  <surface><resource type="datafile">
    <resource-datafile>global</resource-datafile>
  <resource-ident>GroundPieces/Misc/stoneblock3</resource-ident>
  </resource></surface>
  <position>
    <x-pos>359</x-pos>
    <y-pos>206</y-pos>
    <z-pos>0</z-pos>
  </position>
</groundpiece>

<groundpiece type="ground">
  <surface><resource type="datafile">
    <resource-datafile>global</resource-datafile>
  <resource-ident>Hotspots/pillar2</resource-ident>
  </resource></surface>
  <position>
    <x-pos>178</x-pos>
    <y-pos>692</y-pos>
    <z-pos>0</z-pos>
  </position>
</groundpiece>

<groundpiece type="ground">
  <surface><resource type="datafile">
    <resource-datafile>global</resource-datafile>
  <resource-ident>Hotspots/pillar2</resource-ident>
  </resource></surface>
  <position>
    <x-pos>568</x-pos>
    <y-pos>692</y-pos>
    <z-pos>0</z-pos>
  </position>
</groundpiece>

<groundpiece type="ground">
  <surface><resource type="datafile">
    <resource-datafile>global</resource-datafile>
  <resource-ident>GroundPieces/Misc/smallbrickpiece</resource-ident>
  </resource></surface>
  <position>
    <x-pos>526</x-pos>
    <y-pos>616</y-pos>
    <z-pos>0</z-pos>
  </position>
</groundpiece>

<groundpiece type="ground">
  <surface><resource type="datafile">
    <resource-datafile>global</resource-datafile>
  <resource-ident>GroundPieces/Misc/smallbrickpiece</resource-ident>
  </resource></surface>
  <position>
    <x-pos>178</x-pos>
    <y-pos>617</y-pos>
    <z-pos>0</z-pos>
  </position>
</groundpiece>

<groundpiece type="ground">
  <surface><resource type="datafile">
    <resource-datafile>global</resource-datafile>
  <resource-ident>GroundPieces/Misc/smallbrickpiece</resource-ident>
  </resource></surface>
  <position>
    <x-pos>553</x-pos>
    <y-pos>654</y-pos>
    <z-pos>0</z-pos>
  </position>
</groundpiece>

<groundpiece type="ground">
  <surface><resource type="datafile">
    <resource-datafile>global</resource-datafile>
  <resource-ident>GroundPieces/Misc/smallbrickpiece</resource-ident>
  </resource></surface>
  <position>
    <x-pos>157</x-pos>
    <y-pos>655</y-pos>
    <z-pos>0</z-pos>
  </position>
</groundpiece>

<groundpiece type="ground">
  <surface><resource type="datafile">
    <resource-datafile>global</resource-datafile>
  <resource-ident>Hotspots/pillar1</resource-ident>
  </resource></surface>
  <position>
    <x-pos>168</x-pos>
    <y-pos>381</y-pos>
    <z-pos>0</z-pos>
  </position>
</groundpiece>

<groundpiece type="ground">
  <surface><resource type="datafile">
    <resource-datafile>global</resource-datafile>
  <resource-ident>Hotspots/pillar1</resource-ident>
  </resource></surface>
  <position>
    <x-pos>576</x-pos>
    <y-pos>380</y-pos>
    <z-pos>0</z-pos>
  </position>
</groundpiece>

<groundpiece type="ground">
  <surface><resource type="datafile">
    <resource-datafile>global</resource-datafile>
  <resource-ident>GroundPieces/Misc/way_left</resource-ident>
  </resource></surface>
  <position>
    <x-pos>302</x-pos>
    <y-pos>125</y-pos>
    <z-pos>0</z-pos>
  </position>
</groundpiece>

<groundpiece type="ground">
  <surface><resource type="datafile">
    <resource-datafile>global</resource-datafile>
  <resource-ident>GroundPieces/Misc/way_left</resource-ident>
  </resource></surface>
  <position>
    <x-pos>286</x-pos>
    <y-pos>390</y-pos>
    <z-pos>0</z-pos>
  </position>
</groundpiece>

<groundpiece type="ground">
  <surface><resource type="datafile">
    <resource-datafile>global</resource-datafile>
  <resource-ident>GroundPieces/Misc/way_right</resource-ident>
  </resource></surface>
  <position>
    <x-pos>383</x-pos>
    <y-pos>126</y-pos>
    <z-pos>0</z-pos>
  </position>
</groundpiece>

<groundpiece type="ground">
  <surface><resource type="datafile">
    <resource-datafile>global</resource-datafile>
  <resource-ident>GroundPieces/Misc/way_right</resource-ident>
  </resource></surface>
  <position>
    <x-pos>367</x-pos>
    <y-pos>391</y-pos>
    <z-pos>0</z-pos>
  </position>
</groundpiece>

<groundpiece type="ground">
  <surface><resource type="datafile">
    <resource-datafile>global</resource-datafile>
  <resource-ident>GroundPieces/Misc/middleprickpiece</resource-ident>
  </resource></surface>
  <position>
    <x-pos>479</x-pos>
    <y-pos>541</y-pos>
    <z-pos>0</z-pos>
  </position>
</groundpiece>

<groundpiece type="ground">
  <surface><resource type="datafile">
    <resource-datafile>global</resource-datafile>
  <resource-ident>GroundPieces/Misc/middleprickpiece</resource-ident>
  </resource></surface>
  <position>
    <x-pos>156</x-pos>
    <y-pos>542</y-pos>
    <z-pos>0</z-pos>
  </position>
</groundpiece>

<entrance>
  <position>
    <x-pos>369</x-pos>
    <y-pos>48</y-pos>
    <z-pos>0</z-pos>
  </position>
  <type>generic</type>
  <direction>left</direction>
  <release-rate>15</release-rate>
</entrance>

<exit>
  <position>
    <x-pos>316</x-pos>
    <y-pos>723</y-pos>
    <z-pos>0</z-pos>
  </position>
  <surface><resource type="datafile">
    <resource-datafile>exits</resource-datafile>
  <resource-ident>Exits/desert</resource-ident>
  </resource></surface>
</exit>

  <start-position>
  <position>
    <x-pos>372</x-pos>
    <y-pos>54</y-pos>
    <z-pos>1000</z-pos>
  </position>
  </start-position>

</pingus-level>

