<?xml version="1.0"  encoding="ISO-8859-1"?>

<pingus-level>
  <version>1</version>
  <global>
    <levelname lang="en">Crystal Cave - Level 4</levelname>
    <description lang="en">Bang!</description>
    <author>Gunter</author>
    <number-of-pingus>22</number-of-pingus>
    <number-to-save>1</number-to-save>
    <time>-1</time>
    <width>800</width>
    <height>800</height>
    <difficulty>40</difficulty>
    <playable>1</playable>
    <comment></comment>
    <music>none</music>
  </global>

  <action-list>
    <blocker count="16"/>
    <bomber count="20"/>
  </action-list>

<background type="surface">
  <surface><resource type="datafile">
    <resource-datafile>textures</resource-datafile>
  <resource-ident>textures/blueflame</resource-ident>
    <modifier>ROT0</modifier>
  </resource></surface>
  <color>
    <red>0.1</red>
    <green>0.1</green>
    <blue>0.7</blue>
    <alpha>0.5</alpha>
  </color>
  <scroll-x>0</scroll-x>
  <scroll-y>0</scroll-y>
  <para-x>0.8</para-x>
  <para-y>0.8</para-y>
  <stretch-x>0</stretch-x>
  <stretch-y>0</stretch-y>
  <keep-aspect>0</keep-aspect>
  <position>
    <x-pos>8</x-pos>
    <y-pos>10</y-pos>
    <z-pos>-150</z-pos>
  </position>
</background>

<worldobj type="groundpiece">
  <type>ground</type>
  <surface><resource type="datafile">
    <resource-datafile>groundpieces-ground</resource-datafile>
  <resource-ident>crystal/diagcrystal</resource-ident>
    <modifier>ROT270</modifier>
  </resource></surface>
  <position>
    <x-pos>622</x-pos>
    <y-pos>546</y-pos>
    <z-pos>0</z-pos>
  </position>
</worldobj>

<entrance>
  <position>
    <x-pos>359.255</x-pos>
    <y-pos>98.898</y-pos>
    <z-pos>0</z-pos>
  </position>
  <type>generic</type>
  <direction>right</direction>
  <release-rate>250</release-rate>
  <owner-id>0</owner-id>
</entrance>

<worldobj type="groundpiece">
  <type>solid</type>
  <surface><resource type="datafile">
    <resource-datafile>groundpieces-ground</resource-datafile>
  <resource-ident>crystal/hexcrystal</resource-ident>
    <modifier>ROT0</modifier>
  </resource></surface>
  <position>
    <x-pos>115</x-pos>
    <y-pos>229</y-pos>
    <z-pos>0</z-pos>
  </position>
</worldobj>

<worldobj type="groundpiece">
  <type>solid</type>
  <surface><resource type="datafile">
    <resource-datafile>groundpieces-ground</resource-datafile>
  <resource-ident>crystal/hexcrystal</resource-ident>
    <modifier>ROT0</modifier>
  </resource></surface>
  <position>
    <x-pos>199</x-pos>
    <y-pos>315</y-pos>
    <z-pos>0</z-pos>
  </position>
</worldobj>

<worldobj type="groundpiece">
  <type>solid</type>
  <surface><resource type="datafile">
    <resource-datafile>groundpieces-ground</resource-datafile>
  <resource-ident>crystal/hexcrystal</resource-ident>
    <modifier>ROT0</modifier>
  </resource></surface>
  <position>
    <x-pos>201</x-pos>
    <y-pos>408</y-pos>
    <z-pos>0</z-pos>
  </position>
</worldobj>

<worldobj type="groundpiece">
  <type>ground</type>
  <surface><resource type="datafile">
    <resource-datafile>groundpieces-ground</resource-datafile>
  <resource-ident>crystal/diagcrystal</resource-ident>
    <modifier>ROT270</modifier>
  </resource></surface>
  <position>
    <x-pos>318</x-pos>
    <y-pos>300</y-pos>
    <z-pos>0</z-pos>
  </position>
</worldobj>

<worldobj type="groundpiece">
  <type>solid</type>
  <surface><resource type="datafile">
    <resource-datafile>groundpieces-ground</resource-datafile>
  <resource-ident>crystal/hexcrystal</resource-ident>
    <modifier>ROT0</modifier>
  </resource></surface>
  <position>
    <x-pos>476</x-pos>
    <y-pos>484</y-pos>
    <z-pos>0</z-pos>
  </position>
</worldobj>

<worldobj type="groundpiece">
  <type>ground</type>
  <surface><resource type="datafile">
    <resource-datafile>groundpieces-ground</resource-datafile>
  <resource-ident>crystal/diagcrystal</resource-ident>
    <modifier>ROT270</modifier>
  </resource></surface>
  <position>
    <x-pos>429</x-pos>
    <y-pos>424</y-pos>
    <z-pos>0</z-pos>
  </position>
</worldobj>

<worldobj type="groundpiece">
  <type>solid</type>
  <surface><resource type="datafile">
    <resource-datafile>groundpieces-ground</resource-datafile>
  <resource-ident>crystal/hexcrystal</resource-ident>
    <modifier>ROT0</modifier>
  </resource></surface>
  <position>
    <x-pos>356</x-pos>
    <y-pos>487</y-pos>
    <z-pos>0</z-pos>
  </position>
</worldobj>

<worldobj type="groundpiece">
  <type>solid</type>
  <surface><resource type="datafile">
    <resource-datafile>groundpieces-ground</resource-datafile>
  <resource-ident>crystal/hexcrystal</resource-ident>
    <modifier>ROT0</modifier>
  </resource></surface>
  <position>
    <x-pos>406</x-pos>
    <y-pos>295</y-pos>
    <z-pos>0</z-pos>
  </position>
</worldobj>

<worldobj type="groundpiece">
  <type>solid</type>
  <surface><resource type="datafile">
    <resource-datafile>groundpieces-ground</resource-datafile>
  <resource-ident>crystal/hexcrystal</resource-ident>
    <modifier>ROT0</modifier>
  </resource></surface>
  <position>
    <x-pos>526</x-pos>
    <y-pos>301</y-pos>
    <z-pos>0</z-pos>
  </position>
</worldobj>

<worldobj type="groundpiece">
  <type>solid</type>
  <surface><resource type="datafile">
    <resource-datafile>groundpieces-ground</resource-datafile>
  <resource-ident>crystal/hexcrystal</resource-ident>
    <modifier>ROT0</modifier>
  </resource></surface>
  <position>
    <x-pos>397</x-pos>
    <y-pos>768</y-pos>
    <z-pos>0</z-pos>
  </position>
</worldobj>

<worldobj type="groundpiece">
  <type>solid</type>
  <surface><resource type="datafile">
    <resource-datafile>groundpieces-ground</resource-datafile>
  <resource-ident>crystal/hexcrystal</resource-ident>
    <modifier>ROT0</modifier>
  </resource></surface>
  <position>
    <x-pos>503</x-pos>
    <y-pos>192</y-pos>
    <z-pos>0</z-pos>
  </position>
</worldobj>

<worldobj type="groundpiece">
  <type>ground</type>
  <surface><resource type="datafile">
    <resource-datafile>groundpieces-ground</resource-datafile>
  <resource-ident>crystal/diagcrystal</resource-ident>
    <modifier>ROT270</modifier>
  </resource></surface>
  <position>
    <x-pos>316</x-pos>
    <y-pos>680</y-pos>
    <z-pos>0</z-pos>
  </position>
</worldobj>

<worldobj type="groundpiece">
  <type>ground</type>
  <surface><resource type="datafile">
    <resource-datafile>groundpieces-ground</resource-datafile>
  <resource-ident>crystal/diagcrystal</resource-ident>
    <modifier>ROT270</modifier>
  </resource></surface>
  <position>
    <x-pos>182</x-pos>
    <y-pos>540</y-pos>
    <z-pos>0</z-pos>
  </position>
</worldobj>

<worldobj type="groundpiece">
  <type>solid</type>
  <surface><resource type="datafile">
    <resource-datafile>groundpieces-ground</resource-datafile>
  <resource-ident>crystal/hexcrystal</resource-ident>
    <modifier>ROT0</modifier>
  </resource></surface>
  <position>
    <x-pos>107</x-pos>
    <y-pos>466</y-pos>
    <z-pos>0</z-pos>
  </position>
</worldobj>

<worldobj type="groundpiece">
  <type>solid</type>
  <surface><resource type="datafile">
    <resource-datafile>groundpieces-ground</resource-datafile>
  <resource-ident>crystal/hexcrystal</resource-ident>
    <modifier>ROT0</modifier>
  </resource></surface>
  <position>
    <x-pos>294</x-pos>
    <y-pos>572</y-pos>
    <z-pos>0</z-pos>
  </position>
</worldobj>

<worldobj type="groundpiece">
  <type>solid</type>
  <surface><resource type="datafile">
    <resource-datafile>groundpieces-ground</resource-datafile>
  <resource-ident>crystal/hexcrystal</resource-ident>
    <modifier>ROT0</modifier>
  </resource></surface>
  <position>
    <x-pos>486</x-pos>
    <y-pos>768</y-pos>
    <z-pos>0</z-pos>
  </position>
</worldobj>

<worldobj type="groundpiece">
  <type>solid</type>
  <surface><resource type="datafile">
    <resource-datafile>groundpieces-ground</resource-datafile>
  <resource-ident>crystal/hexcrystal</resource-ident>
    <modifier>ROT0</modifier>
  </resource></surface>
  <position>
    <x-pos>53</x-pos>
    <y-pos>566</y-pos>
    <z-pos>0</z-pos>
  </position>
</worldobj>

<worldobj type="groundpiece">
  <type>solid</type>
  <surface><resource type="datafile">
    <resource-datafile>groundpieces-ground</resource-datafile>
  <resource-ident>crystal/hexcrystal</resource-ident>
    <modifier>ROT0</modifier>
  </resource></surface>
  <position>
    <x-pos>642</x-pos>
    <y-pos>331</y-pos>
    <z-pos>0</z-pos>
  </position>
</worldobj>

<worldobj type="groundpiece">
  <type>ground</type>
  <surface><resource type="datafile">
    <resource-datafile>groundpieces-ground</resource-datafile>
  <resource-ident>crystal/diagcrystal</resource-ident>
    <modifier>ROT270</modifier>
  </resource></surface>
  <position>
    <x-pos>676</x-pos>
    <y-pos>433</y-pos>
    <z-pos>0</z-pos>
  </position>
</worldobj>

<worldobj type="groundpiece">
  <type>solid</type>
  <surface><resource type="datafile">
    <resource-datafile>groundpieces-ground</resource-datafile>
  <resource-ident>crystal/hexcrystal</resource-ident>
    <modifier>ROT0</modifier>
  </resource></surface>
  <position>
    <x-pos>652</x-pos>
    <y-pos>499</y-pos>
    <z-pos>0</z-pos>
  </position>
</worldobj>

<worldobj type="groundpiece">
  <type>solid</type>
  <surface><resource type="datafile">
    <resource-datafile>groundpieces-ground</resource-datafile>
  <resource-ident>crystal/hexcrystal</resource-ident>
    <modifier>ROT0</modifier>
  </resource></surface>
  <position>
    <x-pos>122</x-pos>
    <y-pos>661</y-pos>
    <z-pos>0</z-pos>
  </position>
</worldobj>

<worldobj type="groundpiece">
  <type>solid</type>
  <surface><resource type="datafile">
    <resource-datafile>groundpieces-ground</resource-datafile>
  <resource-ident>crystal/hexcrystal</resource-ident>
    <modifier>ROT0</modifier>
  </resource></surface>
  <position>
    <x-pos>244</x-pos>
    <y-pos>736</y-pos>
    <z-pos>0</z-pos>
  </position>
</worldobj>

<worldobj type="groundpiece">
  <type>solid</type>
  <surface><resource type="datafile">
    <resource-datafile>groundpieces-ground</resource-datafile>
  <resource-ident>crystal/hexcrystal</resource-ident>
    <modifier>ROT0</modifier>
  </resource></surface>
  <position>
    <x-pos>345</x-pos>
    <y-pos>766</y-pos>
    <z-pos>0</z-pos>
  </position>
</worldobj>

<worldobj type="groundpiece">
  <type>solid</type>
  <surface><resource type="datafile">
    <resource-datafile>groundpieces-ground</resource-datafile>
  <resource-ident>crystal/hexcrystal</resource-ident>
    <modifier>ROT0</modifier>
  </resource></surface>
  <position>
    <x-pos>441</x-pos>
    <y-pos>767</y-pos>
    <z-pos>0</z-pos>
  </position>
</worldobj>

<worldobj type="groundpiece">
  <type>solid</type>
  <surface><resource type="datafile">
    <resource-datafile>groundpieces-ground</resource-datafile>
  <resource-ident>crystal/hexcrystal</resource-ident>
    <modifier>ROT0</modifier>
  </resource></surface>
  <position>
    <x-pos>638</x-pos>
    <y-pos>717</y-pos>
    <z-pos>0</z-pos>
  </position>
</worldobj>

<worldobj type="groundpiece">
  <type>solid</type>
  <surface><resource type="datafile">
    <resource-datafile>groundpieces-ground</resource-datafile>
  <resource-ident>crystal/hexcrystal</resource-ident>
    <modifier>ROT0</modifier>
  </resource></surface>
  <position>
    <x-pos>536</x-pos>
    <y-pos>770</y-pos>
    <z-pos>0</z-pos>
  </position>
</worldobj>

<worldobj type="groundpiece">
  <type>solid</type>
  <surface><resource type="datafile">
    <resource-datafile>groundpieces-ground</resource-datafile>
  <resource-ident>crystal/hexcrystal</resource-ident>
    <modifier>ROT0</modifier>
  </resource></surface>
  <position>
    <x-pos>652</x-pos>
    <y-pos>538</y-pos>
    <z-pos>0</z-pos>
  </position>
</worldobj>

<worldobj type="groundpiece">
  <type>solid</type>
  <surface><resource type="datafile">
    <resource-datafile>groundpieces-ground</resource-datafile>
  <resource-ident>crystal/hexcrystal</resource-ident>
    <modifier>ROT0</modifier>
  </resource></surface>
  <position>
    <x-pos>643</x-pos>
    <y-pos>572</y-pos>
    <z-pos>0</z-pos>
  </position>
</worldobj>

<worldobj type="groundpiece">
  <type>ground</type>
  <surface><resource type="datafile">
    <resource-datafile>groundpieces-ground</resource-datafile>
  <resource-ident>crystal/diagcrystal</resource-ident>
    <modifier>ROT270</modifier>
  </resource></surface>
  <position>
    <x-pos>413</x-pos>
    <y-pos>483</y-pos>
    <z-pos>0</z-pos>
  </position>
</worldobj>

<worldobj type="groundpiece">
  <type>solid</type>
  <surface><resource type="datafile">
    <resource-datafile>groundpieces-ground</resource-datafile>
  <resource-ident>crystal/hexcrystal</resource-ident>
    <modifier>ROT0</modifier>
  </resource></surface>
  <position>
    <x-pos>475</x-pos>
    <y-pos>520</y-pos>
    <z-pos>0</z-pos>
  </position>
</worldobj>

<worldobj type="groundpiece">
  <type>ground</type>
  <surface><resource type="datafile">
    <resource-datafile>groundpieces-ground</resource-datafile>
  <resource-ident>crystal/diagcrystal</resource-ident>
    <modifier>ROT270</modifier>
  </resource></surface>
  <position>
    <x-pos>409</x-pos>
    <y-pos>614</y-pos>
    <z-pos>0</z-pos>
  </position>
</worldobj>

<worldobj type="groundpiece">
  <type>ground</type>
  <surface><resource type="datafile">
    <resource-datafile>groundpieces-ground</resource-datafile>
  <resource-ident>crystal/diagcrystal</resource-ident>
    <modifier>ROT270</modifier>
  </resource></surface>
  <position>
    <x-pos>398</x-pos>
    <y-pos>562</y-pos>
    <z-pos>0</z-pos>
  </position>
</worldobj>

<worldobj type="groundpiece">
  <type>solid</type>
  <surface><resource type="datafile">
    <resource-datafile>groundpieces-ground</resource-datafile>
  <resource-ident>crystal/hexcrystal</resource-ident>
    <modifier>ROT0</modifier>
  </resource></surface>
  <position>
    <x-pos>281</x-pos>
    <y-pos>129</y-pos>
    <z-pos>0</z-pos>
  </position>
</worldobj>

<worldobj type="groundpiece">
  <type>solid</type>
  <surface><resource type="datafile">
    <resource-datafile>groundpieces-ground</resource-datafile>
  <resource-ident>crystal/hexcrystal</resource-ident>
    <modifier>ROT0</modifier>
  </resource></surface>
  <position>
    <x-pos>377</x-pos>
    <y-pos>127</y-pos>
    <z-pos>0</z-pos>
  </position>
</worldobj>

<worldobj type="groundpiece">
  <type>ground</type>
  <surface><resource type="datafile">
    <resource-datafile>groundpieces-ground</resource-datafile>
  <resource-ident>crystal/diagcrystal</resource-ident>
    <modifier>ROT270</modifier>
  </resource></surface>
  <position>
    <x-pos>508</x-pos>
    <y-pos>124</y-pos>
    <z-pos>0</z-pos>
  </position>
</worldobj>

<worldobj type="groundpiece">
  <type>ground</type>
  <surface><resource type="datafile">
    <resource-datafile>groundpieces-ground</resource-datafile>
  <resource-ident>crystal/diagcrystal</resource-ident>
    <modifier>ROT270</modifier>
  </resource></surface>
  <position>
    <x-pos>60</x-pos>
    <y-pos>194</y-pos>
    <z-pos>0</z-pos>
  </position>
</worldobj>

<worldobj type="groundpiece">
  <type>solid</type>
  <surface><resource type="datafile">
    <resource-datafile>groundpieces-ground</resource-datafile>
  <resource-ident>crystal/hexcrystal</resource-ident>
    <modifier>ROT0</modifier>
  </resource></surface>
  <position>
    <x-pos>-37</x-pos>
    <y-pos>109</y-pos>
    <z-pos>0</z-pos>
  </position>
</worldobj>

<worldobj type="groundpiece">
  <type>ground</type>
  <surface><resource type="datafile">
    <resource-datafile>groundpieces-ground</resource-datafile>
  <resource-ident>crystal/diagcrystal</resource-ident>
    <modifier>ROT270</modifier>
  </resource></surface>
  <position>
    <x-pos>667</x-pos>
    <y-pos>663</y-pos>
    <z-pos>0</z-pos>
  </position>
</worldobj>

<exit use-old-pos-handling="0">
  <position>
    <x-pos>545.898</x-pos>
    <y-pos>768.021</y-pos>
    <z-pos>0</z-pos>
  </position>
  <surface><resource type="datafile">
    <resource-datafile>exits</resource-datafile>
  <resource-ident>exits/crystal</resource-ident>
    <modifier>ROT0</modifier>
  </resource></surface>
  <owner-id>0</owner-id></exit>

<worldobj type="groundpiece">
  <type>solid</type>
  <surface><resource type="datafile">
    <resource-datafile>groundpieces-ground</resource-datafile>
  <resource-ident>crystal/hexcrystal</resource-ident>
    <modifier>ROT0</modifier>
  </resource></surface>
  <position>
    <x-pos>-63</x-pos>
    <y-pos>625</y-pos>
    <z-pos>0</z-pos>
  </position>
</worldobj>

<worldobj type="groundpiece">
  <type>solid</type>
  <surface><resource type="datafile">
    <resource-datafile>groundpieces-ground</resource-datafile>
  <resource-ident>crystal/hexcrystal</resource-ident>
    <modifier>ROT0</modifier>
  </resource></surface>
  <position>
    <x-pos>-30</x-pos>
    <y-pos>415</y-pos>
    <z-pos>0</z-pos>
  </position>
</worldobj>

<worldobj type="groundpiece">
  <type>ground</type>
  <surface><resource type="datafile">
    <resource-datafile>groundpieces-ground</resource-datafile>
  <resource-ident>crystal/diagcrystal</resource-ident>
    <modifier>ROT270</modifier>
  </resource></surface>
  <position>
    <x-pos>55</x-pos>
    <y-pos>389</y-pos>
    <z-pos>0</z-pos>
  </position>
</worldobj>

<worldobj type="groundpiece">
  <type>solid</type>
  <surface><resource type="datafile">
    <resource-datafile>groundpieces-ground</resource-datafile>
  <resource-ident>crystal/hexcrystal</resource-ident>
    <modifier>ROT0</modifier>
  </resource></surface>
  <position>
    <x-pos>686</x-pos>
    <y-pos>76</y-pos>
    <z-pos>0</z-pos>
  </position>
</worldobj>

<worldobj type="groundpiece">
  <type>solid</type>
  <surface><resource type="datafile">
    <resource-datafile>groundpieces-ground</resource-datafile>
  <resource-ident>crystal/hexcrystal</resource-ident>
    <modifier>ROT0</modifier>
  </resource></surface>
  <position>
    <x-pos>600</x-pos>
    <y-pos>-36</y-pos>
    <z-pos>0</z-pos>
  </position>
</worldobj>

<worldobj type="groundpiece">
  <type>ground</type>
  <surface><resource type="datafile">
    <resource-datafile>groundpieces-ground</resource-datafile>
  <resource-ident>crystal/diagcrystal</resource-ident>
    <modifier>ROT270</modifier>
  </resource></surface>
  <position>
    <x-pos>708</x-pos>
    <y-pos>-13</y-pos>
    <z-pos>0</z-pos>
  </position>
</worldobj>

<worldobj type="groundpiece">
  <type>solid</type>
  <surface><resource type="datafile">
    <resource-datafile>groundpieces-ground</resource-datafile>
  <resource-ident>crystal/hexcrystal</resource-ident>
    <modifier>ROT0</modifier>
  </resource></surface>
  <position>
    <x-pos>468</x-pos>
    <y-pos>-74</y-pos>
    <z-pos>0</z-pos>
  </position>
</worldobj>

<worldobj type="groundpiece">
  <type>ground</type>
  <surface><resource type="datafile">
    <resource-datafile>groundpieces-ground</resource-datafile>
  <resource-ident>crystal/diagcrystal</resource-ident>
    <modifier>ROT270</modifier>
  </resource></surface>
  <position>
    <x-pos>375</x-pos>
    <y-pos>-41</y-pos>
    <z-pos>0</z-pos>
  </position>
</worldobj>

<worldobj type="groundpiece">
  <type>solid</type>
  <surface><resource type="datafile">
    <resource-datafile>groundpieces-ground</resource-datafile>
  <resource-ident>crystal/hexcrystal</resource-ident>
    <modifier>ROT0</modifier>
  </resource></surface>
  <position>
    <x-pos>-66</x-pos>
    <y-pos>7</y-pos>
    <z-pos>0</z-pos>
  </position>
</worldobj>

<worldobj type="groundpiece">
  <type>ground</type>
  <surface><resource type="datafile">
    <resource-datafile>groundpieces-ground</resource-datafile>
  <resource-ident>crystal/diagcrystal</resource-ident>
    <modifier>ROT270</modifier>
  </resource></surface>
  <position>
    <x-pos>20</x-pos>
    <y-pos>-49</y-pos>
    <z-pos>0</z-pos>
  </position>
</worldobj>

<worldobj type="groundpiece">
  <type>solid</type>
  <surface><resource type="datafile">
    <resource-datafile>groundpieces-ground</resource-datafile>
  <resource-ident>crystal/hexcrystal</resource-ident>
    <modifier>ROT0</modifier>
  </resource></surface>
  <position>
    <x-pos>104</x-pos>
    <y-pos>-99</y-pos>
    <z-pos>0</z-pos>
  </position>
</worldobj>

<worldobj type="groundpiece">
  <type>solid</type>
  <surface><resource type="datafile">
    <resource-datafile>groundpieces-ground</resource-datafile>
  <resource-ident>crystal/hexcrystal</resource-ident>
    <modifier>ROT0</modifier>
  </resource></surface>
  <position>
    <x-pos>219</x-pos>
    <y-pos>-101</y-pos>
    <z-pos>0</z-pos>
  </position>
</worldobj>

<worldobj type="groundpiece">
  <type>ground</type>
  <surface><resource type="datafile">
    <resource-datafile>groundpieces-ground</resource-datafile>
  <resource-ident>crystal/diagcrystal</resource-ident>
    <modifier>ROT270</modifier>
  </resource></surface>
  <position>
    <x-pos>736</x-pos>
    <y-pos>256</y-pos>
    <z-pos>0</z-pos>
  </position>
</worldobj>

<worldobj type="groundpiece">
  <type>solid</type>
  <surface><resource type="datafile">
    <resource-datafile>groundpieces-ground</resource-datafile>
  <resource-ident>crystal/hexcrystal</resource-ident>
    <modifier>ROT0</modifier>
  </resource></surface>
  <position>
    <x-pos>757</x-pos>
    <y-pos>137</y-pos>
    <z-pos>0</z-pos>
  </position>
</worldobj>

<worldobj type="groundpiece">
  <type>ground</type>
  <surface><resource type="datafile">
    <resource-datafile>groundpieces-ground</resource-datafile>
  <resource-ident>crystal/diagcrystal</resource-ident>
    <modifier>ROT270</modifier>
  </resource></surface>
  <position>
    <x-pos>202</x-pos>
    <y-pos>94</y-pos>
    <z-pos>0</z-pos>
  </position>
</worldobj>

  <start-position>
  <position>
    <x-pos>61</x-pos>
    <y-pos>22</y-pos>
    <z-pos>1000</z-pos>
  </position>
  </start-position>

</pingus-level>

