<?xml version="1.0"  encoding="ISO-8859-1"?>

<pingus-level>
  <global>
    <levelname lang="en">Learning to dig</levelname>
    <description lang="en"></description>
    <author>Ingo Ruhnke &lt;grumbel@gmx.de&gt;</author>
    <number-of-pingus>10</number-of-pingus>
    <number-to-save>5</number-to-save>
    <time>-1</time>
    <width>1400</width>
    <height>700</height>
    <difficulty>0</difficulty>
    <playable>1</playable>
    <comment>first level for the story mode, tutorial island</comment>
  </global>

  <action-list>
    <digger count="10"/>
  </action-list>

<background type="surface">
  <surface><resource type="datafile">
    <resource-datafile>textures</resource-datafile>
  <resource-ident>textures/clouds</resource-ident>
    <modifier>ROT0</modifier>
  </resource></surface>
  <color>
    <red>0</red>
    <green>0</green>
    <blue>0</blue>
    <alpha>0</alpha>
  </color>
  <scroll-x>3</scroll-x>
  <scroll-y>0</scroll-y>
  <para-x>0.5</para-x>
  <para-y>0.5</para-y>
  <stretch-x>0</stretch-x>
  <stretch-y>1</stretch-y>
  <position>
    <x-pos>-103</x-pos>
    <y-pos>-143.12</y-pos>
    <z-pos>-150</z-pos>
  </position>
</background>

<liquid use-old-width-handling="0">
  <surface><resource type="datafile">
    <resource-datafile>liquids</resource-datafile>
  <resource-ident>Liquid/slime</resource-ident>
    <modifier>ROT0</modifier>
  </resource></surface>
  <position>
    <x-pos>-19.52</x-pos>
    <y-pos>629</y-pos>
    <z-pos>-100</z-pos>
  </position>
  <width>23</width>
  <speed>0</speed>
</liquid>

<hotspot>
  <surface><resource type="datafile">
    <resource-datafile>hotspots</resource-datafile>
  <resource-ident>signposts/digger</resource-ident>
    <modifier>ROT0</modifier>
  </resource></surface>
  <position>
    <x-pos>796.28</x-pos>
    <y-pos>302.92</y-pos>
    <z-pos>-50</z-pos>
  </position>
  <speed>-1</speed>
  <parallax>1</parallax>
</hotspot>

<hotspot>
  <surface><resource type="datafile">
    <resource-datafile>hotspots</resource-datafile>
  <resource-ident>signposts/arrow_south</resource-ident>
    <modifier>ROT0</modifier>
  </resource></surface>
  <position>
    <x-pos>760.28</x-pos>
    <y-pos>301.92</y-pos>
    <z-pos>-50</z-pos>
  </position>
  <speed>-1</speed>
  <parallax>1</parallax>
</hotspot>

<worldobj type="groundpiece">
  <type>ground</type>
  <surface><resource type="datafile">
    <resource-datafile>groundpieces-ground</resource-datafile>
  <resource-ident>snow/piece7</resource-ident>
    <modifier>ROT0</modifier>
  </resource></surface>
  <position>
    <x-pos>305.84</x-pos>
    <y-pos>351.48</y-pos>
    <z-pos>0</z-pos>
  </position>
</worldobj>

<worldobj type="groundpiece">
  <type>ground</type>
  <surface><resource type="datafile">
    <resource-datafile>groundpieces-ground</resource-datafile>
  <resource-ident>snow/piece7</resource-ident>
    <modifier>ROT0</modifier>
  </resource></surface>
  <position>
    <x-pos>267.84</x-pos>
    <y-pos>379.48</y-pos>
    <z-pos>0</z-pos>
  </position>
</worldobj>

<worldobj type="groundpiece">
  <type>ground</type>
  <surface><resource type="datafile">
    <resource-datafile>groundpieces-ground</resource-datafile>
  <resource-ident>snow/piece9</resource-ident>
    <modifier>ROT0</modifier>
  </resource></surface>
  <position>
    <x-pos>653.84</x-pos>
    <y-pos>344.48</y-pos>
    <z-pos>0</z-pos>
  </position>
</worldobj>

<worldobj type="groundpiece">
  <type>ground</type>
  <surface><resource type="datafile">
    <resource-datafile>groundpieces-ground</resource-datafile>
  <resource-ident>snow/piece9</resource-ident>
    <modifier>ROT90</modifier>
  </resource></surface>
  <position>
    <x-pos>373.84</x-pos>
    <y-pos>362.48</y-pos>
    <z-pos>0</z-pos>
  </position>
</worldobj>

<worldobj type="groundpiece">
  <type>ground</type>
  <surface><resource type="datafile">
    <resource-datafile>groundpieces-ground</resource-datafile>
  <resource-ident>misc/stone7</resource-ident>
    <modifier>ROT0</modifier>
  </resource></surface>
  <position>
    <x-pos>332.48</x-pos>
    <y-pos>260.52</y-pos>
    <z-pos>0</z-pos>
  </position>
</worldobj>

<worldobj type="groundpiece">
  <type>ground</type>
  <surface><resource type="datafile">
    <resource-datafile>groundpieces-ground</resource-datafile>
  <resource-ident>snow/piece9</resource-ident>
    <modifier>ROT90FLIP</modifier>
  </resource></surface>
  <position>
    <x-pos>288.84</x-pos>
    <y-pos>317.48</y-pos>
    <z-pos>0</z-pos>
  </position>
</worldobj>

<worldobj type="groundpiece">
  <type>ground</type>
  <surface><resource type="datafile">
    <resource-datafile>groundpieces-ground</resource-datafile>
  <resource-ident>misc/stone7</resource-ident>
    <modifier>ROT0</modifier>
  </resource></surface>
  <position>
    <x-pos>298.48</x-pos>
    <y-pos>297.52</y-pos>
    <z-pos>0</z-pos>
  </position>
</worldobj>

<worldobj type="groundpiece">
  <type>ground</type>
  <surface><resource type="datafile">
    <resource-datafile>groundpieces-ground</resource-datafile>
  <resource-ident>misc/stone7</resource-ident>
    <modifier>ROT0</modifier>
  </resource></surface>
  <position>
    <x-pos>366.48</x-pos>
    <y-pos>305.52</y-pos>
    <z-pos>0</z-pos>
  </position>
</worldobj>

<worldobj type="groundpiece">
  <type>ground</type>
  <surface><resource type="datafile">
    <resource-datafile>groundpieces-ground</resource-datafile>
  <resource-ident>misc/stone7</resource-ident>
    <modifier>ROT0</modifier>
  </resource></surface>
  <position>
    <x-pos>880.48</x-pos>
    <y-pos>260.52</y-pos>
    <z-pos>0</z-pos>
  </position>
</worldobj>

<worldobj type="groundpiece">
  <type>ground</type>
  <surface><resource type="datafile">
    <resource-datafile>groundpieces-ground</resource-datafile>
  <resource-ident>snow/piece9</resource-ident>
    <modifier>ROT0</modifier>
  </resource></surface>
  <position>
    <x-pos>318.84</x-pos>
    <y-pos>535.48</y-pos>
    <z-pos>0</z-pos>
  </position>
</worldobj>

<worldobj type="groundpiece">
  <type>ground</type>
  <surface><resource type="datafile">
    <resource-datafile>groundpieces-ground</resource-datafile>
  <resource-ident>snow/piece9</resource-ident>
    <modifier>ROT0</modifier>
  </resource></surface>
  <position>
    <x-pos>500.84</x-pos>
    <y-pos>534.48</y-pos>
    <z-pos>0</z-pos>
  </position>
</worldobj>

<worldobj type="groundpiece">
  <type>ground</type>
  <surface><resource type="datafile">
    <resource-datafile>groundpieces-ground</resource-datafile>
  <resource-ident>snow/piece7</resource-ident>
    <modifier>ROT0</modifier>
  </resource></surface>
  <position>
    <x-pos>217.84</x-pos>
    <y-pos>483.48</y-pos>
    <z-pos>0</z-pos>
  </position>
</worldobj>

<worldobj type="groundpiece">
  <type>ground</type>
  <surface><resource type="datafile">
    <resource-datafile>groundpieces-ground</resource-datafile>
  <resource-ident>snow/piece9</resource-ident>
    <modifier>ROT0</modifier>
  </resource></surface>
  <position>
    <x-pos>657.84</x-pos>
    <y-pos>535.48</y-pos>
    <z-pos>0</z-pos>
  </position>
</worldobj>

<worldobj type="groundpiece">
  <type>ground</type>
  <surface><resource type="datafile">
    <resource-datafile>groundpieces-ground</resource-datafile>
  <resource-ident>snow/piece7</resource-ident>
    <modifier>ROT0</modifier>
  </resource></surface>
  <position>
    <x-pos>844.84</x-pos>
    <y-pos>484.48</y-pos>
    <z-pos>0</z-pos>
  </position>
</worldobj>

<worldobj type="groundpiece">
  <type>ground</type>
  <surface><resource type="datafile">
    <resource-datafile>groundpieces-ground</resource-datafile>
  <resource-ident>snow/piece9</resource-ident>
    <modifier>ROT180</modifier>
  </resource></surface>
  <position>
    <x-pos>498.84</x-pos>
    <y-pos>344.48</y-pos>
    <z-pos>0</z-pos>
  </position>
</worldobj>

<worldobj type="groundpiece">
  <type>ground</type>
  <surface><resource type="datafile">
    <resource-datafile>groundpieces-ground</resource-datafile>
  <resource-ident>misc/stone7</resource-ident>
    <modifier>ROT0</modifier>
  </resource></surface>
  <position>
    <x-pos>914.48</x-pos>
    <y-pos>305.52</y-pos>
    <z-pos>0</z-pos>
  </position>
</worldobj>

<worldobj type="groundpiece">
  <type>ground</type>
  <surface><resource type="datafile">
    <resource-datafile>groundpieces-ground</resource-datafile>
  <resource-ident>misc/stone7</resource-ident>
    <modifier>ROT0</modifier>
  </resource></surface>
  <position>
    <x-pos>846.48</x-pos>
    <y-pos>297.52</y-pos>
    <z-pos>0</z-pos>
  </position>
</worldobj>

<worldobj type="groundpiece">
  <type>ground</type>
  <surface><resource type="datafile">
    <resource-datafile>groundpieces-ground</resource-datafile>
  <resource-ident>snow/piece7</resource-ident>
    <modifier>ROT0FLIP</modifier>
  </resource></surface>
  <position>
    <x-pos>286.84</x-pos>
    <y-pos>482.48</y-pos>
    <z-pos>0</z-pos>
  </position>
</worldobj>

<worldobj type="groundpiece">
  <type>ground</type>
  <surface><resource type="datafile">
    <resource-datafile>groundpieces-ground</resource-datafile>
  <resource-ident>snow/piece9</resource-ident>
    <modifier>ROT0</modifier>
  </resource></surface>
  <position>
    <x-pos>779.84</x-pos>
    <y-pos>343.48</y-pos>
    <z-pos>0</z-pos>
  </position>
</worldobj>

<worldobj type="groundpiece">
  <type>ground</type>
  <surface><resource type="datafile">
    <resource-datafile>groundpieces-ground</resource-datafile>
  <resource-ident>snow/piece7</resource-ident>
    <modifier>ROT0FLIP</modifier>
  </resource></surface>
  <position>
    <x-pos>883.84</x-pos>
    <y-pos>362.48</y-pos>
    <z-pos>0</z-pos>
  </position>
</worldobj>

<worldobj type="groundpiece">
  <type>ground</type>
  <surface><resource type="datafile">
    <resource-datafile>groundpieces-ground</resource-datafile>
  <resource-ident>snow/piece9</resource-ident>
    <modifier>ROT90FLIP</modifier>
  </resource></surface>
  <position>
    <x-pos>872.84</x-pos>
    <y-pos>342.48</y-pos>
    <z-pos>0</z-pos>
  </position>
</worldobj>

<worldobj type="groundpiece">
  <type>ground</type>
  <surface><resource type="datafile">
    <resource-datafile>groundpieces-ground</resource-datafile>
  <resource-ident>snow/piece9</resource-ident>
    <modifier>ROT0</modifier>
  </resource></surface>
  <position>
    <x-pos>337.84</x-pos>
    <y-pos>340.48</y-pos>
    <z-pos>0</z-pos>
  </position>
</worldobj>

<worldobj type="groundpiece">
  <type>ground</type>
  <surface><resource type="datafile">
    <resource-datafile>groundpieces-ground</resource-datafile>
  <resource-ident>snow/piece7</resource-ident>
    <modifier>ROT0FLIP</modifier>
  </resource></surface>
  <position>
    <x-pos>896.84</x-pos>
    <y-pos>437.48</y-pos>
    <z-pos>0</z-pos>
  </position>
</worldobj>

<worldobj type="groundpiece">
  <type>ground</type>
  <surface><resource type="datafile">
    <resource-datafile>groundpieces-ground</resource-datafile>
  <resource-ident>snow/piece3</resource-ident>
    <modifier>ROT0</modifier>
  </resource></surface>
  <position>
    <x-pos>441.84</x-pos>
    <y-pos>533.48</y-pos>
    <z-pos>0</z-pos>
  </position>
</worldobj>

<worldobj type="groundpiece">
  <type>ground</type>
  <surface><resource type="datafile">
    <resource-datafile>groundpieces-ground</resource-datafile>
  <resource-ident>snow/piece3</resource-ident>
    <modifier>ROT0</modifier>
  </resource></surface>
  <position>
    <x-pos>548.84</x-pos>
    <y-pos>533.48</y-pos>
    <z-pos>0</z-pos>
  </position>
</worldobj>

<worldobj type="groundpiece">
  <type>ground</type>
  <surface><resource type="datafile">
    <resource-datafile>groundpieces-ground</resource-datafile>
  <resource-ident>snow/piece3</resource-ident>
    <modifier>ROT0</modifier>
  </resource></surface>
  <position>
    <x-pos>713.84</x-pos>
    <y-pos>533.48</y-pos>
    <z-pos>0</z-pos>
  </position>
</worldobj>

<worldobj type="groundpiece">
  <type>ground</type>
  <surface><resource type="datafile">
    <resource-datafile>groundpieces-ground</resource-datafile>
  <resource-ident>snow/piece3</resource-ident>
    <modifier>ROT0</modifier>
  </resource></surface>
  <position>
    <x-pos>305.84</x-pos>
    <y-pos>339.48</y-pos>
    <z-pos>0</z-pos>
  </position>
</worldobj>

<worldobj type="groundpiece">
  <type>ground</type>
  <surface><resource type="datafile">
    <resource-datafile>groundpieces-ground</resource-datafile>
  <resource-ident>snow/piece3</resource-ident>
    <modifier>ROT0</modifier>
  </resource></surface>
  <position>
    <x-pos>405.84</x-pos>
    <y-pos>344.48</y-pos>
    <z-pos>0</z-pos>
  </position>
</worldobj>

<worldobj type="groundpiece">
  <type>ground</type>
  <surface><resource type="datafile">
    <resource-datafile>groundpieces-ground</resource-datafile>
  <resource-ident>snow/piece3</resource-ident>
    <modifier>ROT0</modifier>
  </resource></surface>
  <position>
    <x-pos>570.84</x-pos>
    <y-pos>344.48</y-pos>
    <z-pos>0</z-pos>
  </position>
</worldobj>

<worldobj type="groundpiece">
  <type>ground</type>
  <surface><resource type="datafile">
    <resource-datafile>groundpieces-ground</resource-datafile>
  <resource-ident>snow/piece3</resource-ident>
    <modifier>ROT0</modifier>
  </resource></surface>
  <position>
    <x-pos>730.84</x-pos>
    <y-pos>342.48</y-pos>
    <z-pos>0</z-pos>
  </position>
</worldobj>

<worldobj type="groundpiece">
  <type>ground</type>
  <surface><resource type="datafile">
    <resource-datafile>groundpieces-ground</resource-datafile>
  <resource-ident>snow/piece2</resource-ident>
    <modifier>ROT0</modifier>
  </resource></surface>
  <position>
    <x-pos>893.48</x-pos>
    <y-pos>347.52</y-pos>
    <z-pos>0</z-pos>
  </position>
</worldobj>

<worldobj type="groundpiece">
  <type>ground</type>
  <surface><resource type="datafile">
    <resource-datafile>groundpieces-ground</resource-datafile>
  <resource-ident>snow/piece2</resource-ident>
    <modifier>ROT0</modifier>
  </resource></surface>
  <position>
    <x-pos>952.48</x-pos>
    <y-pos>357.52</y-pos>
    <z-pos>0</z-pos>
  </position>
</worldobj>

<worldobj type="groundpiece">
  <type>ground</type>
  <surface><resource type="datafile">
    <resource-datafile>groundpieces-ground</resource-datafile>
  <resource-ident>snow/ice1</resource-ident>
    <modifier>ROT0</modifier>
  </resource></surface>
  <position>
    <x-pos>311.48</x-pos>
    <y-pos>348.52</y-pos>
    <z-pos>0</z-pos>
  </position>
</worldobj>

<worldobj type="groundpiece">
  <type>ground</type>
  <surface><resource type="datafile">
    <resource-datafile>groundpieces-ground</resource-datafile>
  <resource-ident>snow/ice1</resource-ident>
    <modifier>ROT0</modifier>
  </resource></surface>
  <position>
    <x-pos>842.48</x-pos>
    <y-pos>347.52</y-pos>
    <z-pos>0</z-pos>
  </position>
</worldobj>

<worldobj type="groundpiece">
  <type>ground</type>
  <surface><resource type="datafile">
    <resource-datafile>groundpieces-ground</resource-datafile>
  <resource-ident>snow/ice1</resource-ident>
    <modifier>ROT0</modifier>
  </resource></surface>
  <position>
    <x-pos>447.48</x-pos>
    <y-pos>348.52</y-pos>
    <z-pos>0</z-pos>
  </position>
</worldobj>

<worldobj type="groundpiece">
  <type>ground</type>
  <surface><resource type="datafile">
    <resource-datafile>groundpieces-ground</resource-datafile>
  <resource-ident>snow/piece7</resource-ident>
    <modifier>ROT0</modifier>
  </resource></surface>
  <position>
    <x-pos>244.84</x-pos>
    <y-pos>429.48</y-pos>
    <z-pos>0</z-pos>
  </position>
</worldobj>

<worldobj type="groundpiece">
  <type>ground</type>
  <surface><resource type="datafile">
    <resource-datafile>groundpieces-ground</resource-datafile>
  <resource-ident>snow/piece7</resource-ident>
    <modifier>ROT0</modifier>
  </resource></surface>
  <position>
    <x-pos>178.84</x-pos>
    <y-pos>537.48</y-pos>
    <z-pos>0</z-pos>
  </position>
</worldobj>

<worldobj type="groundpiece">
  <type>ground</type>
  <surface><resource type="datafile">
    <resource-datafile>groundpieces-ground</resource-datafile>
  <resource-ident>snow/ice1</resource-ident>
    <modifier>ROT0</modifier>
  </resource></surface>
  <position>
    <x-pos>446.48</x-pos>
    <y-pos>540.52</y-pos>
    <z-pos>0</z-pos>
  </position>
</worldobj>

<worldobj type="groundpiece">
  <type>ground</type>
  <surface><resource type="datafile">
    <resource-datafile>groundpieces-ground</resource-datafile>
  <resource-ident>snow/ice2</resource-ident>
    <modifier>ROT0</modifier>
  </resource></surface>
  <position>
    <x-pos>593.48</x-pos>
    <y-pos>539.52</y-pos>
    <z-pos>0</z-pos>
  </position>
</worldobj>

<worldobj type="groundpiece">
  <type>ground</type>
  <surface><resource type="datafile">
    <resource-datafile>groundpieces-ground</resource-datafile>
  <resource-ident>snow/ice2</resource-ident>
    <modifier>ROT0</modifier>
  </resource></surface>
  <position>
    <x-pos>796.48</x-pos>
    <y-pos>538.52</y-pos>
    <z-pos>0</z-pos>
  </position>
</worldobj>

<worldobj type="groundpiece">
  <type>ground</type>
  <surface><resource type="datafile">
    <resource-datafile>groundpieces-ground</resource-datafile>
  <resource-ident>snow/ice2</resource-ident>
    <modifier>ROT0</modifier>
  </resource></surface>
  <position>
    <x-pos>578.48</x-pos>
    <y-pos>350.52</y-pos>
    <z-pos>0</z-pos>
  </position>
</worldobj>

<worldobj type="groundpiece">
  <type>ground</type>
  <surface><resource type="datafile">
    <resource-datafile>groundpieces-ground</resource-datafile>
  <resource-ident>snow/ice2</resource-ident>
    <modifier>ROT0</modifier>
  </resource></surface>
  <position>
    <x-pos>737.48</x-pos>
    <y-pos>348.52</y-pos>
    <z-pos>0</z-pos>
  </position>
</worldobj>

<exit use-old-pos-handling="0">
  <position>
    <x-pos>810.48</x-pos>
    <y-pos>535.52</y-pos>
    <z-pos>0</z-pos>
  </position>
  <surface><resource type="datafile">
    <resource-datafile>exits</resource-datafile>
  <resource-ident>exits/ice2</resource-ident>
    <modifier>ROT0</modifier>
  </resource></surface>
  <owner-id>0</owner-id></exit>

<worldobj type="groundpiece">
  <type>ground</type>
  <surface><resource type="datafile">
    <resource-datafile>groundpieces-ground</resource-datafile>
  <resource-ident>snow/piece7</resource-ident>
    <modifier>ROT0</modifier>
  </resource></surface>
  <position>
    <x-pos>392.84</x-pos>
    <y-pos>579.48</y-pos>
    <z-pos>0</z-pos>
  </position>
</worldobj>

<worldobj type="groundpiece">
  <type>ground</type>
  <surface><resource type="datafile">
    <resource-datafile>groundpieces-ground</resource-datafile>
  <resource-ident>snow/piece7</resource-ident>
    <modifier>ROT0FLIP</modifier>
  </resource></surface>
  <position>
    <x-pos>350.84</x-pos>
    <y-pos>578.48</y-pos>
    <z-pos>0</z-pos>
  </position>
</worldobj>

<worldobj type="groundpiece">
  <type>ground</type>
  <surface><resource type="datafile">
    <resource-datafile>groundpieces-ground</resource-datafile>
  <resource-ident>snow/piece7</resource-ident>
    <modifier>ROT0</modifier>
  </resource></surface>
  <position>
    <x-pos>733.84</x-pos>
    <y-pos>571.48</y-pos>
    <z-pos>0</z-pos>
  </position>
</worldobj>

<worldobj type="groundpiece">
  <type>ground</type>
  <surface><resource type="datafile">
    <resource-datafile>groundpieces-ground</resource-datafile>
  <resource-ident>snow/piece9</resource-ident>
    <modifier>ROT0</modifier>
  </resource></surface>
  <position>
    <x-pos>492.84</x-pos>
    <y-pos>560.48</y-pos>
    <z-pos>0</z-pos>
  </position>
</worldobj>

<entrance>
  <position>
    <x-pos>495.28</x-pos>
    <y-pos>261.92</y-pos>
    <z-pos>0</z-pos>
  </position>
  <type>generic</type>
  <direction>right</direction>
  <release-rate>150</release-rate>
  <owner-id>0</owner-id>
</entrance>

<worldobj type="groundpiece">
  <type>ground</type>
  <surface><resource type="datafile">
    <resource-datafile>groundpieces-ground</resource-datafile>
  <resource-ident>snow/piece7</resource-ident>
    <modifier>ROT0</modifier>
  </resource></surface>
  <position>
    <x-pos>110.84</x-pos>
    <y-pos>599.48</y-pos>
    <z-pos>0</z-pos>
  </position>
</worldobj>

<worldobj type="groundpiece">
  <type>ground</type>
  <surface><resource type="datafile">
    <resource-datafile>groundpieces-ground</resource-datafile>
  <resource-ident>snow/piece7</resource-ident>
    <modifier>ROT0FLIP</modifier>
  </resource></surface>
  <position>
    <x-pos>1056.84</x-pos>
    <y-pos>590.48</y-pos>
    <z-pos>0</z-pos>
  </position>
</worldobj>

<worldobj type="groundpiece">
  <type>ground</type>
  <surface><resource type="datafile">
    <resource-datafile>groundpieces-ground</resource-datafile>
  <resource-ident>snow/piece9</resource-ident>
    <modifier>ROT0</modifier>
  </resource></surface>
  <position>
    <x-pos>493.84</x-pos>
    <y-pos>614.48</y-pos>
    <z-pos>0</z-pos>
  </position>
</worldobj>

<worldobj type="groundpiece">
  <type>ground</type>
  <surface><resource type="datafile">
    <resource-datafile>groundpieces-ground</resource-datafile>
  <resource-ident>snow/piece9</resource-ident>
    <modifier>ROT0FLIP</modifier>
  </resource></surface>
  <position>
    <x-pos>851.84</x-pos>
    <y-pos>623.48</y-pos>
    <z-pos>0</z-pos>
  </position>
</worldobj>

<worldobj type="groundpiece">
  <type>ground</type>
  <surface><resource type="datafile">
    <resource-datafile>groundpieces-ground</resource-datafile>
  <resource-ident>snow/piece9</resource-ident>
    <modifier>ROT0FLIP</modifier>
  </resource></surface>
  <position>
    <x-pos>866.84</x-pos>
    <y-pos>563.48</y-pos>
    <z-pos>0</z-pos>
  </position>
</worldobj>

<worldobj type="groundpiece">
  <type>ground</type>
  <surface><resource type="datafile">
    <resource-datafile>groundpieces-ground</resource-datafile>
  <resource-ident>snow/piece7</resource-ident>
    <modifier>ROT0FLIP</modifier>
  </resource></surface>
  <position>
    <x-pos>923.84</x-pos>
    <y-pos>492.48</y-pos>
    <z-pos>0</z-pos>
  </position>
</worldobj>

<worldobj type="groundpiece">
  <type>ground</type>
  <surface><resource type="datafile">
    <resource-datafile>groundpieces-ground</resource-datafile>
  <resource-ident>snow/piece7</resource-ident>
    <modifier>ROT0</modifier>
  </resource></surface>
  <position>
    <x-pos>251.84</x-pos>
    <y-pos>584.48</y-pos>
    <z-pos>0</z-pos>
  </position>
</worldobj>

<liquid use-old-width-handling="0">
  <surface><resource type="datafile">
    <resource-datafile>liquids</resource-datafile>
  <resource-ident>Liquid/slime</resource-ident>
    <modifier>ROT0</modifier>
  </resource></surface>
  <position>
    <x-pos>-49.52</x-pos>
    <y-pos>643</y-pos>
    <z-pos>50</z-pos>
  </position>
  <width>23</width>
  <speed>0</speed>
</liquid>

  <start-position>
  <position>
    <x-pos>638</x-pos>
    <y-pos>423</y-pos>
    <z-pos>1000</z-pos>
  </position>
  </start-position>

</pingus-level>

